universalpython/__init__.py
universalpython/universalpython.py
universalpython/languages/cs/default.yaml
universalpython/languages/de/default.yaml
universalpython/languages/emoji/default.yaml
universalpython/languages/fr/default.yaml
universalpython/languages/ga/default.yaml
universalpython/languages/hi/default.yaml
universalpython/languages/hu/default.yaml
universalpython/languages/ko/default.yaml
universalpython/languages/tr/default.yaml
universalpython/languages/ua/default.yaml
universalpython/languages/ur/default.yaml
universalpython/modes/__init__.py
universalpython/modes/lex.py
universalpython-0.1.8.dist-info/licenses/LICENSE
universalpython-0.1.8.dist-info/METADATA
universalpython-0.1.8.dist-info/WHEEL
universalpython-0.1.8.dist-info/entry_points.txt
universalpython-0.1.8.dist-info/top_level.txt
universalpython-0.1.8.dist-info/RECORD
