Metadata-Version: 2.4
Name: universalpython
Version: 0.1.8
Summary: UniversalPython - Write Python in your native language
Author-email: Saad Bazaz <saadbazaz@hotmail.com>
Project-URL: Homepage, https://universalpython.github.io
Project-URL: Repository, https://github.com/UniversalPython/UniversalPython
Project-URL: Issues, https://github.com/UniversalPython/UniversalPython/issues
Keywords: i18n,localization,programming-language
Classifier: Development Status :: 4 - Beta
Classifier: Intended Audience :: Developers
Classifier: Intended Audience :: Education
Classifier: Programming Language :: Python :: 3
Classifier: License :: OSI Approved :: MIT License
Classifier: Operating System :: OS Independent
Classifier: Topic :: Software Development :: Internationalization
Classifier: Topic :: Software Development :: Interpreters
Requires-Python: >=3.7
License-File: LICENSE
Requires-Dist: ply>=3.11
Requires-Dist: PyYAML>=6.0
Requires-Dist: Unidecode>=1.3.6
Dynamic: license-file
